pyams_content/__init__.py
pyams_content/include.py
pyams_content/component/__init__.py
pyams_content/component/association/__init__.py
pyams_content/component/association/container.py
pyams_content/component/association/interfaces.py
pyams_content/component/association/paragraph.py
pyams_content/component/association/skin/__init__.py
pyams_content/component/association/skin/interfaces.py
pyams_content/component/association/skin/paragraph.py
pyams_content/component/association/skin/templates/association-default.pt
pyams_content/component/association/skin/templates/association-viewlet.pt
pyams_content/component/association/zmi/__init__.py
pyams_content/component/association/zmi/container.py
pyams_content/component/association/zmi/interfaces.py
pyams_content/component/association/zmi/paragraph.py
pyams_content/component/association/zmi/templates/associations-table.pt
pyams_content/component/calendar/__init__.py
pyams_content/component/cards/__init__.py
pyams_content/component/cards/interfaces.py
pyams_content/component/cards/skin/__init__.py
pyams_content/component/cards/skin/interfaces.py
pyams_content/component/cards/skin/templates/cards-masonry.pt
pyams_content/component/cards/skin/templates/cards.pt
pyams_content/component/cards/zmi/__init__.py
pyams_content/component/contact/__init__.py
pyams_content/component/contact/interfaces.py
pyams_content/component/contact/portlet/__init__.py
pyams_content/component/contact/portlet/interfaces.py
pyams_content/component/contact/portlet/skin/__init__.py
pyams_content/component/contact/portlet/skin/interfaces.py
pyams_content/component/contact/portlet/skin/zmi.py
pyams_content/component/contact/portlet/skin/templates/contact-default.pt
pyams_content/component/contact/portlet/zmi/__init__.py
pyams_content/component/contact/portlet/zmi/templates/contact-preview.pt
pyams_content/component/contact/skin/__init__.py
pyams_content/component/contact/skin/interfaces.py
pyams_content/component/contact/skin/zmi.py
pyams_content-2.7.0.dist-info/LICENSE
pyams_content-2.7.0.dist-info/METADATA
pyams_content-2.7.0.dist-info/WHEEL
pyams_content-2.7.0.dist-info/entry_points.txt
pyams_content-2.7.0.dist-info/namespace_packages.txt
pyams_content-2.7.0.dist-info/top_level.txt
pyams_content-2.7.0.dist-info/RECORD
