Metadata-Version: 2.1
Name: pyams-content
Version: 2.7.0
Summary: PyAMS content management package
Home-page: https://pyams.readthedocs.io
Author: Thierry Florac
Author-email: tflorac@ulthar.net
License: ZPL
Keywords: Pyramid PyAMS CMS
Classifier: License :: OSI Approved :: Zope Public License
Classifier: Development Status :: 4 - Beta
Classifier: Programming Language :: Python
Classifier: Framework :: Pyramid
Classifier: Topic :: Software Development :: Libraries :: Python Modules
License-File: LICENSE
Requires-Dist: setuptools
Requires-Dist: fanstatic
Requires-Dist: hypatia
Requires-Dist: persistent
Requires-Dist: pyams-catalog
Requires-Dist: pyams-fields
Requires-Dist: pyams-file
Requires-Dist: pyams-form >=2.1.0
Requires-Dist: pyams-gis
Requires-Dist: pyams-i18n
Requires-Dist: pyams-i18n-views
Requires-Dist: pyams-layer
Requires-Dist: pyams-mail
Requires-Dist: pyams-pagelet
Requires-Dist: pyams-portal
Requires-Dist: pyams-scheduler >=2.7.0
Requires-Dist: pyams-security >=2.2.1
Requires-Dist: pyams-security-views
Requires-Dist: pyams-sequence
Requires-Dist: pyams-site
Requires-Dist: pyams-skin
Requires-Dist: pyams-template
Requires-Dist: pyams-thesaurus
Requires-Dist: pyams-utils >=2.7.6
Requires-Dist: pyams-viewlet
Requires-Dist: pyams-workflow >=2.2.0
Requires-Dist: pyahocorasick
Requires-Dist: pyramid
Requires-Dist: qrcode
Requires-Dist: transaction
Requires-Dist: zope.annotation
Requires-Dist: zope.component
Requires-Dist: zope.container
Requires-Dist: zope.contentprovider
Requires-Dist: zope.copy
Requires-Dist: zope.dublincore
Requires-Dist: zope.interface
Requires-Dist: zope.intid
Requires-Dist: zope.lifecycleevent
Requires-Dist: zope.location
Requires-Dist: zope.schema
Requires-Dist: zope.traversing
Provides-Extra: test
Requires-Dist: pyams-security-views ; extra == 'test'
Requires-Dist: pyams-zmi ; extra == 'test'
Requires-Dist: pyramid-zcml ; extra == 'test'
Requires-Dist: zope.exceptions ; extra == 'test'
